{
    "os": "Linux-5.4.0-74-generic-x86_64-with-debian-buster-sid",
    "python": "3.6.9",
    "heartbeatAt": "2021-06-16T11:03:18.001413",
    "startedAt": "2021-06-16T11:03:16.764421",
    "docker": null,
    "gpu": "TITAN V",
    "gpu_count": 1,
    "cpu_count": 4,
    "cuda": "10.2.89",
    "args": [],
    "state": "running",
    "program": "train.py",
    "codePath": "train.py",
    "git": {
        "remote": "https://github.com/cmosquer/MixedMaskRCNN.git",
        "commit": "d89ce02306701f4961387467b5c2748f2cab4db5"
    },
    "email": "cmosquer@itba.edu.ar",
    "root": "/home/usuariohi/Documentos/Repos/MixedMaskRCNN",
    "host": "usuariohi-Precision-T3600",
    "username": "usuariohi",
    "executable": "/home/usuariohi/anaconda3/envs/pytorch-opacidad/bin/python"
}
